README.txt
bootstrap.py
buildout.cfg
setup.py
svnignore.sh
docs/HISTORY.txt
docs/INSTALL.txt
docs/LICENSE.GPL
docs/LICENSE.txt
src/collective/__init__.py
src/collective.generic.devmode.egg-info/PKG-INFO
src/collective.generic.devmode.egg-info/SOURCES.txt
src/collective.generic.devmode.egg-info/dependency_links.txt
src/collective.generic.devmode.egg-info/entry_points.txt
src/collective.generic.devmode.egg-info/namespace_packages.txt
src/collective.generic.devmode.egg-info/requires.txt
src/collective.generic.devmode.egg-info/top_level.txt
src/collective/generic/__init__.py
src/collective/generic/devmode/__init__.py
src/collective/generic/devmode/commands.py
src/collective/generic/devmode/common.py
src/collective/generic/devmode/devmode.py
src/collective/generic/devmode/tests/__init__.py
src/collective/generic/devmode/tests/globals.py
src/collective/generic/devmode/tests/test_doctests.py