Metadata-Version: 1.0
Name: collective.generic.devmode
Version: 1.0
Summary: Sanitize a plone site for development use.
Home-page: http://pypi.python.org/pypi/collective.generic.devmode
Author: kiorky
Author-email: kiorky@cryptelium.net
License: GPL
Platform: UNKNOWN
Classifier: Programming Language :: Python
Classifier: Topic :: Software Development
